professor.py
professore-0.0.11.dist-info/METADATA
professore-0.0.11.dist-info/WHEEL
professore-0.0.11.dist-info/entry_points.txt
professore-0.0.11.dist-info/top_level.txt
professore-0.0.11.dist-info/RECORD
