Metadata-Version: 2.1
Name: professore
Version: 0.0.11
Summary: List url link, script tags, reponse headers
Home-page: https://github.com/null011/Professore
Author: Noe Macias
Author-email: notnull011@gmail.com
License: UNKNOWN
Project-URL: Bug Tracker, https://github.com/null011/Professore/issues
Platform: UNKNOWN
Classifier: Programming Language :: Python :: 3
Classifier: License :: OSI Approved :: MIT License
Classifier: Operating System :: OS Independent
Requires-Python: >=3.6
Requires-Dist: requests
Requires-Dist: beautifulsoup4
